libroadrunner_tr-1.0.0.data/scripts/roadrunner_tr
libroadrunner_tr-1.0.0.dist-info/METADATA
libroadrunner_tr-1.0.0.dist-info/RECORD
libroadrunner_tr-1.0.0.dist-info/WHEEL
libroadrunner_tr-1.0.0.dist-info/top_level.txt
roadrunner_tr/__init__.py
roadrunner_tr/__main__.py
roadrunner_tr/main.py
